fidac/__init__.py
fidac/evaluate_computer_output.py
fidac/measure_manual.py
fidac/measure_position.py
fidac/mediapipe_detector.py
fidac/overhead_file.py
fidac/pyfeat_detector.py
fidac-0.1.0.dist-info/LICENSE.txt
fidac-0.1.0.dist-info/METADATA
fidac-0.1.0.dist-info/WHEEL
fidac-0.1.0.dist-info/top_level.txt
fidac-0.1.0.dist-info/RECORD
