Metadata-Version: 2.1
Name: fidac
Version: 0.1.0
Summary: insert description
Home-page: https://github.com/yourusername/my_library
Author: Keshav Rastogi
Author-email: keshavrast21@gmail.com
License: MIT
Classifier: Programming Language :: Python :: 3
Classifier: License :: OSI Approved :: MIT License
Classifier: Operating System :: OS Independent
Requires-Python: >=3.9
License-File: LICENSE.txt
Requires-Dist: pandas
Requires-Dist: opencv-python
Requires-Dist: tqdm
Requires-Dist: numpy
Requires-Dist: matplotlib
Requires-Dist: seaborn
